{
  "v": "5.6.5",
  "fr": 29,
  "ip": 0,
  "op": 117,
  "w": 750,
  "h": 1334,
  "nm": "ripple 3",
  "ddd": 0,
  "assets": [],
  "layers": [
    {
      "ddd": 0,
      "ind": 1,
      "ty": 4,
      "nm": "Shape Layer 4",
      "td": 1,
      "sr": 1,
      "ks": {
        "o": {
          "a": 0,
          "k": 100,
          "ix": 11
        },
        "r": {
          "a": 0,
          "k": 0,
          "ix": 10
        },
        "p": {
          "a": 0,
          "k": [
            375,
            667,
            0
          ],
          "ix": 2
        },
        "a": {
          "a": 0,
          "k": [
            -13.156,
            18.328,
            0
          ],
          "ix": 1
        },
        "s": {
          "a": 1,
          "k": [
            {
              "i": {
                "x": [
                  0,
                  0,
                  0.667
                ],
                "y": [
                  1,
                  1,
                  1
                ]
              },
              "o": {
                "x": [
                  0.333,
                  0.333,
                  0.333
                ],
                "y": [
                  0,
                  0,
                  0
                ]
              },
              "t": 23.562,
              "s": [
                0,
                0,
                100
              ]
            },
            {
              "t": 108,
              "s": [
                393,
                393,
                100
              ]
            }
          ],
          "ix": 6
        }
      },
      "ao": 0,
      "shapes": [
        {
          "ty": "gr",
          "it": [
            {
              "ind": 0,
              "ty": "sh",
              "ix": 1,
              "ks": {
                "a": 0,
                "k": {
                  "i": [
                    [
                      -29.81,
                      0
                    ],
                    [
                      0,
                      -29.81
                    ],
                    [
                      29.81,
                      0
                    ],
                    [
                      0,
                      29.81
                    ]
                  ],
                  "o": [
                    [
                      29.81,
                      0
                    ],
                    [
                      0,
                      29.81
                    ],
                    [
                      -29.81,
                      0
                    ],
                    [
                      0,
                      -29.81
                    ]
                  ],
                  "v": [
                    [
                      0,
                      -53.977
                    ],
                    [
                      53.977,
                      0
                    ],
                    [
                      0,
                      53.977
                    ],
                    [
                      -53.977,
                      0
                    ]
                  ],
                  "c": true
                },
                "ix": 2
              },
              "nm": "Path 1",
              "mn": "ADBE Vector Shape - Group",
              "hd": false
            },
            {
              "ty": "fl",
              "c": {
                "a": 0,
                "k": [
                  0,
                  0.160784313725,
                  0.082352941176,
                  1
                ],
                "ix": 4
              },
              "o": {
                "a": 0,
                "k": 100,
                "ix": 5
              },
              "r": 1,
              "bm": 0,
              "nm": "Fill 1",
              "mn": "ADBE Vector Graphic - Fill",
              "hd": false
            },
            {
              "ty": "tr",
              "p": {
                "a": 0,
                "k": [
                  -13.156,
                  18.328
                ],
                "ix": 2
              },
              "a": {
                "a": 0,
                "k": [
                  0,
                  0
                ],
                "ix": 1
              },
              "s": {
                "a": 0,
                "k": [
                  100,
                  100
                ],
                "ix": 3
              },
              "r": {
                "a": 0,
                "k": 0,
                "ix": 6
              },
              "o": {
                "a": 0,
                "k": 100,
                "ix": 7
              },
              "sk": {
                "a": 0,
                "k": 0,
                "ix": 4
              },
              "sa": {
                "a": 0,
                "k": 0,
                "ix": 5
              },
              "nm": "Transform"
            }
          ],
          "nm": "Ellipse 1",
          "np": 3,
          "cix": 2,
          "bm": 0,
          "ix": 1,
          "mn": "ADBE Vector Group",
          "hd": false
        }
      ],
      "ip": 23.5625,
      "op": 108,
      "st": 23.5625,
      "bm": 0
    },
    {
      "ddd": 0,
      "ind": 2,
      "ty": 4,
      "nm": "Shape Layer 3",
      "tt": 2,
      "sr": 1,
      "ks": {
        "o": {
          "a": 0,
          "k": 100,
          "ix": 11
        },
        "r": {
          "a": 0,
          "k": 0,
          "ix": 10
        },
        "p": {
          "a": 0,
          "k": [
            375,
            667,
            0
          ],
          "ix": 2
        },
        "a": {
          "a": 0,
          "k": [
            -13.156,
            18.328,
            0
          ],
          "ix": 1
        },
        "s": {
          "a": 1,
          "k": [
            {
              "i": {
                "x": [
                  0,
                  0,
                  0.667
                ],
                "y": [
                  1,
                  1,
                  1
                ]
              },
              "o": {
                "x": [
                  0.333,
                  0.333,
                  0.333
                ],
                "y": [
                  0,
                  0,
                  0
                ]
              },
              "t": 16.312,
              "s": [
                0,
                0,
                100
              ]
            },
            {
              "t": 102,
              "s": [
                390,
                390,
                100
              ]
            }
          ],
          "ix": 6
        }
      },
      "ao": 0,
      "shapes": [
        {
          "ty": "gr",
          "it": [
            {
              "ind": 0,
              "ty": "sh",
              "ix": 1,
              "ks": {
                "a": 0,
                "k": {
                  "i": [
                    [
                      -29.81,
                      0
                    ],
                    [
                      0,
                      -29.81
                    ],
                    [
                      29.81,
                      0
                    ],
                    [
                      0,
                      29.81
                    ]
                  ],
                  "o": [
                    [
                      29.81,
                      0
                    ],
                    [
                      0,
                      29.81
                    ],
                    [
                      -29.81,
                      0
                    ],
                    [
                      0,
                      -29.81
                    ]
                  ],
                  "v": [
                    [
                      0,
                      -53.977
                    ],
                    [
                      53.977,
                      0
                    ],
                    [
                      0,
                      53.977
                    ],
                    [
                      -53.977,
                      0
                    ]
                  ],
                  "c": true
                },
                "ix": 2
              },
              "nm": "Path 1",
              "mn": "ADBE Vector Shape - Group",
              "hd": false
            },
            {
              "ty": "gf",
              "o": {
                "a": 0,
                "k": 100,
                "ix": 10
              },
              "r": 1,
              "bm": 0,
              "g": {
                "p": 3,
                "k": {
                  "a": 0,
                  "k": [
                    0,
                    0.576,
                    0.784,
                    0.875,
                    0.499,
                    0.288,
                    0.473,
                    0.478,
                    0.998,
                    0,
                    0.161,
                    0.082,
                    0,
                    1,
                    0.5,
                    0.5,
                    1,
                    0
                  ],
                  "ix": 9
                }
              },
              "s": {
                "a": 0,
                "k": [
                  -3.095,
                  -79.739
                ],
                "ix": 5
              },
              "e": {
                "a": 0,
                "k": [
                  -3.676,
                  53.769
                ],
                "ix": 6
              },
              "t": 1,
              "nm": "Gradient Fill 1",
              "mn": "ADBE Vector Graphic - G-Fill",
              "hd": false
            },
            {
              "ty": "tr",
              "p": {
                "a": 0,
                "k": [
                  -12.668,
                  18.426
                ],
                "ix": 2
              },
              "a": {
                "a": 0,
                "k": [
                  0,
                  0
                ],
                "ix": 1
              },
              "s": {
                "a": 0,
                "k": [
                  100,
                  100
                ],
                "ix": 3
              },
              "r": {
                "a": 0,
                "k": 0,
                "ix": 6
              },
              "o": {
                "a": 0,
                "k": 100,
                "ix": 7
              },
              "sk": {
                "a": 0,
                "k": 0,
                "ix": 4
              },
              "sa": {
                "a": 0,
                "k": 0,
                "ix": 5
              },
              "nm": "Transform"
            }
          ],
          "nm": "Ellipse 1",
          "np": 2,
          "cix": 2,
          "bm": 0,
          "ix": 1,
          "mn": "ADBE Vector Group",
          "hd": false
        }
      ],
      "ip": 16.3125,
      "op": 108,
      "st": 16.3125,
      "bm": 0
    },
    {
      "ddd": 0,
      "ind": 3,
      "ty": 4,
      "nm": "Shape Layer 2",
      "td": 1,
      "sr": 1,
      "ks": {
        "o": {
          "a": 0,
          "k": 100,
          "ix": 11
        },
        "r": {
          "a": 0,
          "k": 0,
          "ix": 10
        },
        "p": {
          "a": 0,
          "k": [
            375,
            667,
            0
          ],
          "ix": 2
        },
        "a": {
          "a": 0,
          "k": [
            -13.156,
            18.328,
            0
          ],
          "ix": 1
        },
        "s": {
          "a": 1,
          "k": [
            {
              "i": {
                "x": [
                  0,
                  0,
                  0.667
                ],
                "y": [
                  1,
                  1,
                  1
                ]
              },
              "o": {
                "x": [
                  0.333,
                  0.333,
                  0.333
                ],
                "y": [
                  0,
                  0,
                  0
                ]
              },
              "t": 7.25,
              "s": [
                0,
                0,
                100
              ]
            },
            {
              "t": 98,
              "s": [
                582,
                582,
                100
              ]
            }
          ],
          "ix": 6
        }
      },
      "ao": 0,
      "shapes": [
        {
          "ty": "gr",
          "it": [
            {
              "ind": 0,
              "ty": "sh",
              "ix": 1,
              "ks": {
                "a": 0,
                "k": {
                  "i": [
                    [
                      -29.81,
                      0
                    ],
                    [
                      0,
                      -29.81
                    ],
                    [
                      29.81,
                      0
                    ],
                    [
                      0,
                      29.81
                    ]
                  ],
                  "o": [
                    [
                      29.81,
                      0
                    ],
                    [
                      0,
                      29.81
                    ],
                    [
                      -29.81,
                      0
                    ],
                    [
                      0,
                      -29.81
                    ]
                  ],
                  "v": [
                    [
                      0,
                      -53.977
                    ],
                    [
                      53.977,
                      0
                    ],
                    [
                      0,
                      53.977
                    ],
                    [
                      -53.977,
                      0
                    ]
                  ],
                  "c": true
                },
                "ix": 2
              },
              "nm": "Path 1",
              "mn": "ADBE Vector Shape - Group",
              "hd": false
            },
            {
              "ty": "fl",
              "c": {
                "a": 0,
                "k": [
                  0,
                  0.160784313725,
                  0.082352941176,
                  1
                ],
                "ix": 4
              },
              "o": {
                "a": 0,
                "k": 100,
                "ix": 5
              },
              "r": 1,
              "bm": 0,
              "nm": "Fill 1",
              "mn": "ADBE Vector Graphic - Fill",
              "hd": false
            },
            {
              "ty": "tr",
              "p": {
                "a": 0,
                "k": [
                  -13.156,
                  18.328
                ],
                "ix": 2
              },
              "a": {
                "a": 0,
                "k": [
                  0,
                  0
                ],
                "ix": 1
              },
              "s": {
                "a": 0,
                "k": [
                  100,
                  100
                ],
                "ix": 3
              },
              "r": {
                "a": 0,
                "k": 0,
                "ix": 6
              },
              "o": {
                "a": 0,
                "k": 100,
                "ix": 7
              },
              "sk": {
                "a": 0,
                "k": 0,
                "ix": 4
              },
              "sa": {
                "a": 0,
                "k": 0,
                "ix": 5
              },
              "nm": "Transform"
            }
          ],
          "nm": "Ellipse 1",
          "np": 3,
          "cix": 2,
          "bm": 0,
          "ix": 1,
          "mn": "ADBE Vector Group",
          "hd": false
        }
      ],
      "ip": 7.25,
      "op": 98,
      "st": 7.25,
      "bm": 0
    },
    {
      "ddd": 0,
      "ind": 4,
      "ty": 4,
      "nm": "Shape Layer 1",
      "tt": 2,
      "sr": 1,
      "ks": {
        "o": {
          "a": 0,
          "k": 100,
          "ix": 11
        },
        "r": {
          "a": 0,
          "k": 0,
          "ix": 10
        },
        "p": {
          "a": 0,
          "k": [
            375,
            667,
            0
          ],
          "ix": 2
        },
        "a": {
          "a": 0,
          "k": [
            -13.156,
            18.328,
            0
          ],
          "ix": 1
        },
        "s": {
          "a": 1,
          "k": [
            {
              "i": {
                "x": [
                  0,
                  0,
                  0.667
                ],
                "y": [
                  1,
                  1,
                  1
                ]
              },
              "o": {
                "x": [
                  0.333,
                  0.333,
                  0.333
                ],
                "y": [
                  0,
                  0,
                  0
                ]
              },
              "t": 0,
              "s": [
                0,
                0,
                100
              ]
            },
            {
              "t": 92,
              "s": [
                580,
                580,
                100
              ]
            }
          ],
          "ix": 6
        }
      },
      "ao": 0,
      "shapes": [
        {
          "ty": "gr",
          "it": [
            {
              "ind": 0,
              "ty": "sh",
              "ix": 1,
              "ks": {
                "a": 0,
                "k": {
                  "i": [
                    [
                      -29.81,
                      0
                    ],
                    [
                      0,
                      -29.81
                    ],
                    [
                      29.81,
                      0
                    ],
                    [
                      0,
                      29.81
                    ]
                  ],
                  "o": [
                    [
                      29.81,
                      0
                    ],
                    [
                      0,
                      29.81
                    ],
                    [
                      -29.81,
                      0
                    ],
                    [
                      0,
                      -29.81
                    ]
                  ],
                  "v": [
                    [
                      0,
                      -53.977
                    ],
                    [
                      53.977,
                      0
                    ],
                    [
                      0,
                      53.977
                    ],
                    [
                      -53.977,
                      0
                    ]
                  ],
                  "c": true
                },
                "ix": 2
              },
              "nm": "Path 1",
              "mn": "ADBE Vector Shape - Group",
              "hd": false
            },
            {
              "ty": "gf",
              "o": {
                "a": 0,
                "k": 100,
                "ix": 10
              },
              "r": 1,
              "bm": 0,
              "g": {
                "p": 3,
                "k": {
                  "a": 0,
                  "k": [
                    0,
                    0.576,
                    0.784,
                    0.875,
                    0.4,
                    0.288,
                    0.473,
                    0.478,
                    1,
                    0,
                    0.161,
                    0.082,
                    0,
                    1,
                    0.5,
                    0.5,
                    1,
                    0
                  ],
                  "ix": 9
                }
              },
              "s": {
                "a": 0,
                "k": [
                  2.648,
                  135.703
                ],
                "ix": 5
              },
              "e": {
                "a": 0,
                "k": [
                  1.818,
                  -55.289
                ],
                "ix": 6
              },
              "t": 1,
              "nm": "Gradient Fill 1",
              "mn": "ADBE Vector Graphic - G-Fill",
              "hd": false
            },
            {
              "ty": "tr",
              "p": {
                "a": 0,
                "k": [
                  -13.156,
                  18.328
                ],
                "ix": 2
              },
              "a": {
                "a": 0,
                "k": [
                  0,
                  0
                ],
                "ix": 1
              },
              "s": {
                "a": 0,
                "k": [
                  100,
                  100
                ],
                "ix": 3
              },
              "r": {
                "a": 0,
                "k": 0,
                "ix": 6
              },
              "o": {
                "a": 0,
                "k": 100,
                "ix": 7
              },
              "sk": {
                "a": 0,
                "k": 0,
                "ix": 4
              },
              "sa": {
                "a": 0,
                "k": 0,
                "ix": 5
              },
              "nm": "Transform"
            }
          ],
          "nm": "Ellipse 1",
          "np": 2,
          "cix": 2,
          "bm": 0,
          "ix": 1,
          "mn": "ADBE Vector Group",
          "hd": false
        }
      ],
      "ip": 0,
      "op": 98,
      "st": 0,
      "bm": 0
    }
  ],
  "markers": []
}
